cliMetaTool/__init__.py
cliMetaTool/_const.py
cliMetaTool/meta_change.py
cliMetaTool/meta_change_detect.py
cliMetaTool/utils.py
cliMetaTool/data/blob_config.ini
cli_meta_tool-0.1.0.dist-info/METADATA
cli_meta_tool-0.1.0.dist-info/WHEEL
cli_meta_tool-0.1.0.dist-info/top_level.txt
cli_meta_tool-0.1.0.dist-info/RECORD
