Metadata-Version: 2.1
Name: cli-meta-tool
Version: 0.1.0
Summary: A tool for cli metadata management
Author: Microsoft Corporation
Author-email: azpycli@microsoft.com
License: MIT
Requires-Dist: deepdiff
Requires-Dist: requests
